maloja/__init__.py
maloja/__main__.py
maloja/__pkginfo__.py
maloja/cleanup.py
maloja/images.py
maloja/malojatime.py
maloja/malojauri.py
maloja/server.py
maloja/setup.py
maloja/upgrade.py
maloja/apis/__init__.py
maloja/apis/_apikeys.py
maloja/apis/_base.py
maloja/apis/_exceptions.py
maloja/apis/audioscrobbler.py
maloja/apis/audioscrobbler_legacy.py
maloja/apis/listenbrainz.py
maloja/apis/native_v1.py
maloja/data_files/cache/.maloja_cache_sentinel
maloja/data_files/cache/images/dummy
maloja/data_files/config/.maloja_config_sentinel
maloja/data_files/config/custom_css/customcss.info
maloja/data_files/config/rules/rules.info
maloja/data_files/config/rules/predefined/.gitignore
maloja/data_files/config/rules/predefined/krateng_artistsingroups.tsv
maloja/data_files/config/rules/predefined/krateng_classical.tsv
maloja/data_files/config/rules/predefined/krateng_cpop.tsv
maloja/data_files/config/rules/predefined/krateng_dach.tsv
maloja/data_files/config/rules/predefined/krateng_firefly-soundtrack.tsv
maloja/data_files/config/rules/predefined/krateng_jeremysoule.tsv
maloja/data_files/config/rules/predefined/krateng_jpop.tsv
maloja/data_files/config/rules/predefined/krateng_kpop.tsv
maloja/data_files/config/rules/predefined/krateng_kpopgirlgroups.tsv
maloja/data_files/config/rules/predefined/krateng_lotr-soundtrack.tsv
maloja/data_files/config/rules/predefined/krateng_masseffect.tsv
maloja/data_files/config/rules/predefined/krateng_memes.tsv
maloja/data_files/config/rules/predefined/krateng_monstercat.tsv
maloja/data_files/config/rules/predefined/krateng_redcliff.tsv
maloja/data_files/config/rules/predefined/krateng_specialsymbols.tsv
maloja/data_files/config/rules/predefined/krateng_threelions.tsv
maloja/data_files/config/rules/predefined/predefined.info
maloja/data_files/config/rules/predefined/tdemin_kpop.tsv
maloja/data_files/logs/.maloja_logs_sentinel
maloja/data_files/logs/dbfix/dummy
maloja/data_files/state/.maloja_state_sentinel
maloja/data_files/state/auth/dummy
malojaserver-3.2.3.dist-info/entry_points.txt
malojaserver-3.2.3.dist-info/LICENSE
malojaserver-3.2.3.dist-info/WHEEL
malojaserver-3.2.3.dist-info/METADATA
malojaserver-3.2.3.dist-info/RECORD
