Metadata-Version: 2.3
Name: malojaserver
Version: 3.2.3
Summary: Self-hosted music scrobble database
Keywords: scrobbling,music,selfhosted,database,charts,statistics
Author-email: Johannes Krattenmacher <maloja@dev.krateng.ch>
Requires-Python: >=3.11
Classifier: Programming Language :: Python :: 3
Classifier: License :: OSI Approved :: GNU General Public License v3 (GPLv3)
Classifier: Operating System :: OS Independent
Requires-Dist: bottle>=0.12.16
Requires-Dist: waitress>=2.1.0
Requires-Dist: doreah>=2.0.1, <3
Requires-Dist: nimrodel>=0.8.0
Requires-Dist: setproctitle>=1.1.10
Requires-Dist: jinja2>=3.0.0
Requires-Dist: lru-dict>=1.1.6
Requires-Dist: psutil>=5.8.0
Requires-Dist: sqlalchemy>=2.0
Requires-Dist: python-datauri>=1.1.0
Requires-Dist: requests>=2.27.1
Requires-Dist: setuptools>68.0.0
Requires-Dist: toml>=0.10.2
Requires-Dist: PyYAML>=6.0.1
Requires-Dist: pyvips>=2.1 ; extra == "full"
Project-URL: documentation, https://github.com/krateng/maloja
Project-URL: homepage, https://github.com/krateng/maloja
Project-URL: repository, https://github.com/krateng/maloja
Provides-Extra: full
